passyunk/__init__.py
passyunk/centerline.py
passyunk/data.py
passyunk/landmark.py
passyunk/namestd.py
passyunk/parser.py
passyunk/parser_addr.py
passyunk/pdata/__init__.py
passyunk/pdata/alias.csv
passyunk/pdata/alias_streets.csv
passyunk/pdata/apt.csv
passyunk/pdata/apt_std.csv
passyunk/pdata/apte.csv
passyunk/pdata/centerline.csv
passyunk/pdata/centerline_streets.csv
passyunk/pdata/directional.csv
passyunk/pdata/landmarks.csv
passyunk/pdata/name_switch.csv
passyunk/pdata/saint.csv
passyunk/pdata/std.csv
passyunk/pdata/suffix.csv
passyunk/pdata/update_version.py
passyunk/pdata/version.py
passyunk-2.8.0.dist-info/METADATA
passyunk-2.8.0.dist-info/WHEEL
passyunk-2.8.0.dist-info/top_level.txt
passyunk-2.8.0.dist-info/RECORD
