Metadata-Version: 2.1
Name: passyunk
Version: 2.8.0
Summary: Address parser for City of Philadelphia addresses
Author: Tom Swanson
Author-email: James Midkiff <james.midkiff@phila.gov>
Requires-Python: >=3.7
Requires-Dist: fuzzywuzzy <1.0,>=0.11.1
Requires-Dist: Levenshtein <1.0,>=0.20
Requires-Dist: requests <3.0,>=2.28
Requires-Dist: importlib-metadata <=7.0,>=6.0
